django_webp/__init__.py
django_webp/context_processors.py
django_webp/middleware.py
django_webp/utils.py
django_webp/management/__init__.py
django_webp/management/commands/__init__.py
django_webp/management/commands/clean_webp_images.py
django_webp/templatetags/__init__.py
django_webp/templatetags/webp.py
django_webp-3.0.0.dist-info/LICENSE
django_webp-3.0.0.dist-info/METADATA
django_webp-3.0.0.dist-info/WHEEL
django_webp-3.0.0.dist-info/top_level.txt
django_webp-3.0.0.dist-info/RECORD
