Metadata-Version: 2.1
Name: django-webp
Version: 3.0.0
Summary: Serves a webp version of static images to browsers instead of jpg, gif or png
Author-email: Andre Farzat <andrefarzat@gmail.com>, Daniel Opara <daniel.opara@tufts.edu>
Maintainer-email: Andre Farzat <andrefarzat@gmail.com>, Daniel Opara <daniel.opara@tufts.edu>
License: The MIT License (MIT)
Project-URL: Homepage, http://pypi.python.org/pypi/django-webp/
Keywords: django,webp,python
Classifier: Development Status :: 5 - Production/Stable
Classifier: Intended Audience :: Developers
Classifier: Topic :: Software Development :: Libraries :: Python Modules
Classifier: License :: OSI Approved :: MIT License
Classifier: Programming Language :: Python :: 3
Classifier: Programming Language :: Python :: 3 :: Only
Requires-Python: >=3.5
License-File: LICENSE
Requires-Dist: asgiref >=3.5.0
Requires-Dist: django >=4.0.3
Requires-Dist: pillow >=9.0.1
Requires-Dist: sqlparse >=0.4.2
Requires-Dist: whitenoise >=6.5.0
Provides-Extra: dev
Requires-Dist: pip-tools ; extra == 'dev'
Requires-Dist: pytest ; extra == 'dev'
Requires-Dist: black ; extra == 'dev'
